fps_akernel_task/__init__.py
fps_akernel_task/akernel_task.py
fps_akernel_task/main.py
fps_akernel_task/py.typed
fps_akernel_task-0.1.4.dist-info/METADATA
fps_akernel_task-0.1.4.dist-info/WHEEL
fps_akernel_task-0.1.4.dist-info/entry_points.txt
fps_akernel_task-0.1.4.dist-info/licenses/LICENSE
fps_akernel_task-0.1.4.dist-info/RECORD
