Metadata-Version: 2.4
Name: fps_akernel_task
Version: 0.1.4
Summary: An FPS plugin for the kernel task API
Project-URL: Homepage, https://github.com/davidbrochart/akernel
Author-email: David Brochart <david.brochart@gmail.com>
License: MIT
License-File: LICENSE
Keywords: fastapi,jupyter,plugins,server
Requires-Python: >=3.9
Requires-Dist: akernel>=0.3.4
Requires-Dist: anyio
Requires-Dist: jupyverse-api<0.12.0,>=0.11.0
